MANIFEST.in
README.rst
setup.py
docs/HISTORY.txt
docs/INSTALL.txt
docs/LICENSE.GPL
docs/LICENSE.txt
ftw/__init__.py
ftw.mail.egg-info/PKG-INFO
ftw.mail.egg-info/SOURCES.txt
ftw.mail.egg-info/dependency_links.txt
ftw.mail.egg-info/entry_points.txt
ftw.mail.egg-info/namespace_packages.txt
ftw.mail.egg-info/not-zip-safe
ftw.mail.egg-info/requires.txt
ftw.mail.egg-info/top_level.txt
ftw/mail/__init__.py
ftw/mail/attachment.png
ftw/mail/attachment.py
ftw/mail/config.py
ftw/mail/configure.zcml
ftw/mail/create.py
ftw/mail/emailaddress.py
ftw/mail/exceptions.py
ftw/mail/inbound.py
ftw/mail/indexers.py
ftw/mail/interfaces.py
ftw/mail/lawgiver.zcml
ftw/mail/mail.py
ftw/mail/mailin.py
ftw/mail/mailtab.py
ftw/mail/mta2plone.py
ftw/mail/permissions.zcml
ftw/mail/testing.py
ftw/mail/utils.py
ftw/mail/locales/ftw.mail.pot
ftw/mail/locales/ftw.tabbedview.pot
ftw/mail/locales/de/LC_MESSAGES/ftw.mail.po
ftw/mail/locales/de/LC_MESSAGES/ftw.tabbedview.po
ftw/mail/locales/fr/LC_MESSAGES/ftw.mail.po
ftw/mail/locales/fr/LC_MESSAGES/ftw.tabbedview.po
ftw/mail/mail_templates/mail_in.pt
ftw/mail/mail_templates/view.pt
ftw/mail/profiles/default/metadata.xml
ftw/mail/profiles/default/registry.xml
ftw/mail/profiles/default/rolemap.xml
ftw/mail/profiles/default/types.xml
ftw/mail/profiles/default/types/ftw.mail.mail.xml
ftw/mail/profiles/workspace/metadata.xml
ftw/mail/profiles/workspace/types/TabbedViewFolder.xml
ftw/mail/profiles/workspace/types/Workspace.xml
ftw/mail/tests/__init__.py
ftw/mail/tests/builders.py
ftw/mail/tests/test_emailaddress.py
ftw/mail/tests/test_inbound.py
ftw/mail/tests/test_mail.py
ftw/mail/tests/test_mail_view.py
ftw/mail/tests/test_mailin.py
ftw/mail/tests/test_searchabletext.py
ftw/mail/tests/test_tab.py
ftw/mail/tests/test_utils.py
ftw/mail/tests/test_zipexport.py
ftw/mail/tests/mails/__init__.py
ftw/mail/tests/mails/ascii_7bit.txt
ftw/mail/tests/mails/attachment.txt
ftw/mail/tests/mails/broken_meta_tags.txt
ftw/mail/tests/mails/cropped_filename_attachment.txt
ftw/mail/tests/mails/cropped_filename_attachment2.txt
ftw/mail/tests/mails/eml_mail_attachment_without_filename_extension.eml
ftw/mail/tests/mails/encoded_word_not_separated_by_lwsp.txt
ftw/mail/tests/mails/encoded_word_without_lwsp.txt
