Metadata-Version: 2.1
Name: ftw.mail
Version: 2.8.1
Summary: Provides a mail content type and a mail-in behavior
Home-page: https://github.com/4teamwork/ftw.mail
Author: 4teamwork AG
Author-email: mailto:info@4teamwork.ch
License: GPL2
Classifier: Framework :: Plone
Classifier: Framework :: Plone :: 4.3
Classifier: Intended Audience :: Developers
Classifier: Topic :: Software Development :: Libraries :: Python Modules
Requires-Dist: plone.api
Requires-Dist: plone.app.referenceablebehavior
Requires-Dist: plone.registry
Requires-Dist: plone.dexterity
Requires-Dist: setuptools
Requires-Dist: BeautifulSoup!=4.0b
Requires-Dist: plone.app.dexterity
Requires-Dist: plone.app.registry
Requires-Dist: plone.namedfile[blobs]
Requires-Dist: collective.autopermission
Requires-Dist: collective.dexteritytextindexer
Requires-Dist: plone.supermodel
Requires-Dist: ftw.upgrade>=1.11.0
Requires-Dist: premailer<3.7.0
Provides-Extra: tests
Requires-Dist: ftw.builder; extra == "tests"
Requires-Dist: ftw.testbrowser; extra == "tests"
Requires-Dist: ftw.workspace; extra == "tests"
Requires-Dist: ftw.zipexport; extra == "tests"
Requires-Dist: plone.app.testing; extra == "tests"
Requires-Dist: unittest2; extra == "tests"
